dekdjseed-0.1.11.dist-info/METADATA
dekdjseed-0.1.11.dist-info/WHEEL
dekdjseed-0.1.11.dist-info/entry_points.txt
dekdjseed/__init__.py
dekdjseed/apps.py
dekdjseed/core/__init__.py
dekdjseed/core/fake/__init__.py
dekdjseed/core/fake/core.py
dekdjseed/core/fake/primary.py
dekdjseed/core/fake/providers/__init__.py
dekdjseed/core/fake/providers/common.py
dekdjseed/core/fake/providers/image.py
dekdjseed/core/load/__init__.py
dekdjseed/core/load/samples/settings.yaml
dekdjseed/core/load/settings.yaml
dekdjseed/core/seed.py
dekdjseed/core/utils/__init__.py
dekdjseed/core/utils/model.py
dekdjseed/management/__init__.py
dekdjseed/management/commands/__init__.py
dekdjseed/management/commands/dekdjseed.py
dekdjseed/migrations/__init__.py
dekdjseed-0.1.11.dist-info/RECORD
