Metadata-Version: 2.1
Name: dekdjseed
Version: 0.1.11
Author-Email: sanzenwin <sanzenwin@gmail.com>
License: MIT
Requires-Python: >=3.10
Requires-Dist: Faker<=2.0.1
Requires-Dist: toposort<=1.7
Requires-Dist: microbmp<=0.3.0
Requires-Dist: dekdjtools<1.0.0
